{
  "$schema": "./node_modules/swagger2api-v3/dist/.swagger2api.schema.json",
  "input": "http://localhost:3000/admin/docs/json",
  "output": "./src/api",
  "importTemplate": "import { request } from '@/utils/request';",
  "generator": "typescript",
  "requestStyle": "generic",
  "groupByTags": true,
  "overwrite": true,
  "prefix": "",
  "lint": "prettier --write",
  "methodNameIgnorePrefix": [],
  "addMethodSuffix": true,
  "headerComment": "",
  "filter": {
    "include": {
      "tags": []
    },
    "exclude": {
      "tags": []
    }
  },
  "options": {
    "addComments": true
  }
}